{
  "dataFields": [
    {
      "label": "documentNumber",
      "positionIndex": 0,
      "lineIndex": 0,
      "shapeAttributes": {
        "type": "bboxUR",
        "x": 682,
        "y": 135,
        "width": 288,
        "height": 40
      },
      "type": "documentNumber",
      "postprocessingParameterDict": {
        "validationRegex": "[0-9]{12}",
        "cleanRegex": "[^0-9]",
        "whitelistPattern": "12|[0-9]"
      },
      "preprocessingParameterDict": {
        "splitRatio": 1.28
      }
    },
    {
      "label": "surname",
      "positionIndex": 0,
      "lineIndex": 0,
      "shapeAttributes": {
        "type": "bboxUR",
        "x": 600,
        "y": 195,
        "width": 453,
        "height": 40
      },
      "type": "generic",
      "postprocessingParameterDict": {
        "validationRegex": "[A-ZÄÖÜa-zäöüß\\.\\/\\-\\(\\)\\,\\' ]{1,}",
        "cleanRegex": "[^A-ZÄÖÜa-zäöüß\\.\\/\\-\\(\\)\\,\\' ]",
        "whitelistPattern": "1,|[A-ZÄÖÜa-zäöüß\\.\\/\\-\\(\\)\\,\\' ]"
      },
      "preprocessingParameterDict": {
        "splitRatio": 1.28
      }
    },
    {
      "label": "givenNames",
      "positionIndex": 0,
      "lineIndex": 0,
      "shapeAttributes": {
        "type": "bboxUR",
        "x": 660,
        "y": 288,
        "width": 617,
        "height": 44
      },
      "type": "generic",
      "postprocessingParameterDict": {
        "validationRegex": "[A-ZÄÖÜa-zäöüß\\.\\/\\-\\(\\)\\,\\' ]{1,}",
        "cleanRegex": "[^A-ZÄÖÜa-zäöüß\\.\\/\\-\\(\\)\\,\\' ]",
        "whitelistPattern": "1,|[A-ZÄÖÜa-zäöüß\\.\\/\\-\\(\\)\\,\\' ]"
      },
      "preprocessingParameterDict": {
        "splitRatio": 1.28
      }
    },
    {
      "label": "sex",
      "positionIndex": 0,
      "lineIndex": 0,
      "shapeAttributes": {
        "type": "bboxUR",
        "x": 591,
        "y": 384,
        "width": 59,
        "height": 39
      },
      "type": "generic",
      "postprocessingParameterDict": {
        "validationRegex": "[A-ZÄÖÜa-zäöüß0-9\\.\\/\\-\\(\\)\\,\\' ]{1,}",
        "cleanRegex": "[^A-ZÄÖÜa-zäöüß0-9\\.\\/\\-\\(\\)\\,\\' ]",
        "whitelistPattern": "1,|[A-ZÄÖÜa-zäöüß0-9\\.\\/\\-\\(\\)\\,\\' ]"
      },
      "preprocessingParameterDict": {
        "splitRatio": 1.28
      }
    },
    {
      "label": "dateOfBirth",
      "positionIndex": 0,
      "lineIndex": 0,
      "shapeAttributes": {
        "type": "bboxUR",
        "x": 1008,
        "y": 382,
        "width": 252,
        "height": 44
      },
      "type": "date",
      "postprocessingParameterDict": {
        "cleanRegex": "[^\\d]",
        "whitelistPattern": "1,|[\\d\\-\\/\\. ]",
        "validationRegex": "(0[1-9]|[12][0-9]|3[01]){1}(0[1-9]|1[0-2]){1}(19|20){1}[0-9]{2}"
      },
      "preprocessingParameterDict": {
        "splitRatio": 1.1
      }
    },
    {
      "label": "placeOfBirth",
      "positionIndex": 0,
      "lineIndex": 0,
      "shapeAttributes": {
        "type": "bboxUR",
        "x": 545,
        "y": 428,
        "width": 552,
        "height": 47
      },
      "type": "generic",
      "postprocessingParameterDict": {
        "validationRegex": "[A-ZÄÖÜa-zäöüß0-9\\.\\/\\-\\(\\)\\,\\' ]{1,}",
        "cleanRegex": "[^A-ZÄÖÜa-zäöüß0-9\\.\\/\\-\\(\\)\\,\\' ]",
        "whitelistPattern": "1,|[A-ZÄÖÜa-zäöüß0-9\\.\\/\\-\\(\\)\\,\\' ]"
      },
      "preprocessingParameterDict": {
        "splitRatio": 1.28
      }
    },
    {
      "label": "height",
      "positionIndex": 0,
      "lineIndex": 0,
      "shapeAttributes": {
        "type": "bboxUR",
        "x": 610,
        "y": 474,
        "width": 122,
        "height": 44
      },
      "type": "generic",
      "postprocessingParameterDict": {
        "validationRegex": "[A-ZÄÖÜa-zäöüß0-9\\.\\/\\-\\(\\)\\,\\' ]{1,}",
        "cleanRegex": "[^A-ZÄÖÜa-zäöüß0-9\\.\\/\\-\\(\\)\\,\\' ]",
        "whitelistPattern": "1,|[A-ZÄÖÜa-zäöüß0-9\\.\\/\\-\\(\\)\\,\\' ]"
      },
      "preprocessingParameterDict": {
        "splitRatio": 1.28
      }
    },
    {
      "label": "signature",
      "positionIndex": 0,
      "lineIndex": 0,
      "shapeAttributes": {
        "type": "bboxUR",
        "x": 673,
        "y": 526,
        "width": 769,
        "height": 157
      },
      "type": "image"
    },
    {
      "label": "photo",
      "positionIndex": 0,
      "lineIndex": 0,
      "shapeAttributes": {
        "type": "bboxUR",
        "x": 54,
        "y": 176,
        "width": 423,
        "height": 505
      },
      "type": "image"
    },
    {
      "label": "repulique",
      "positionIndex": 0,
      "lineIndex": 0,
      "shapeAttributes": {
        "type": "bboxUR",
        "x": 74,
        "y": 48,
        "width": 663,
        "height": 59
      },
      "type": "MATCHING"
    },
    {
      "label": "francaise",
      "positionIndex": 0,
      "lineIndex": 0,
      "shapeAttributes": {
        "type": "bboxUR",
        "x": 818,
        "y": 55,
        "width": 600,
        "height": 51
      },
      "type": "MATCHING"
    },
    {
      "label": "carte_nationale_d_identite_n",
      "positionIndex": 0,
      "lineIndex": 0,
      "shapeAttributes": {
        "type": "bboxUR",
        "x": 74,
        "y": 135,
        "width": 580,
        "height": 40
      },
      "type": "MATCHING"
    },
    {
      "label": "nationalite_francaise",
      "positionIndex": 0,
      "lineIndex": 0,
      "shapeAttributes": {
        "type": "bboxUR",
        "x": 1078,
        "y": 135,
        "width": 327,
        "height": 42
      },
      "type": "MATCHING"
    },
    {
      "label": "nom",
      "positionIndex": 0,
      "lineIndex": 0,
      "shapeAttributes": {
        "type": "bboxUR",
        "x": 477,
        "y": 200,
        "width": 109,
        "height": 37
      },
      "type": "MATCHING"
    },
    {
      "label": "presnom",
      "positionIndex": 0,
      "lineIndex": 0,
      "shapeAttributes": {
        "type": "bboxUR",
        "x": 477,
        "y": 297,
        "width": 177,
        "height": 39
      },
      "type": "MATCHING"
    },
    {
      "label": "sexe",
      "positionIndex": 0,
      "lineIndex": 0,
      "shapeAttributes": {
        "type": "bboxUR",
        "x": 477,
        "y": 394,
        "width": 90,
        "height": 34
      },
      "type": "MATCHING"
    },
    {
      "label": "ne_le",
      "positionIndex": 0,
      "lineIndex": 0,
      "shapeAttributes": {
        "type": "bboxUR",
        "x": 847,
        "y": 387,
        "width": 127,
        "height": 44
      },
      "type": "MATCHING"
    },
    {
      "label": "á",
      "positionIndex": 0,
      "lineIndex": 0,
      "shapeAttributes": {
        "type": "bboxUR",
        "x": 475,
        "y": 437,
        "width": 44,
        "height": 40
      },
      "type": "MATCHING"
    },
    {
      "label": "taile",
      "positionIndex": 0,
      "lineIndex": 0,
      "shapeAttributes": {
        "type": "bboxUR",
        "x": 481,
        "y": 485,
        "width": 112,
        "height": 40
      },
      "type": "MATCHING"
    },
    {
      "label": "signature_",
      "positionIndex": 0,
      "lineIndex": 0,
      "shapeAttributes": {
        "type": "bboxUR",
        "x": 486,
        "y": 531,
        "width": 150,
        "height": 37
      },
      "type": "MATCHING"
    },
    {
      "label": "du_titulare",
      "positionIndex": 0,
      "lineIndex": 0,
      "shapeAttributes": {
        "type": "bboxUR",
        "x": 482,
        "y": 568,
        "width": 174,
        "height": 42
      },
      "type": "MATCHING"
    },
    {
      "label": "MRZ",
      "positionIndex": 0,
      "lineIndex": 0,
      "shapeAttributes": {
        "type": "bboxUR",
        "x": 105,
        "y": 713,
        "width": 1283,
        "height": 63
      },
      "type": "MATCHING"
    },
    {
      "label": "MRZ",
      "positionIndex": 0,
      "lineIndex": 1,
      "shapeAttributes": {
        "type": "bboxUR",
        "x": 103,
        "y": 797,
        "width": 1286,
        "height": 56
      },
      "type": "MATCHING"
    }
  ],
  "height": 950,
  "width": 1500,
  "postprocessingParameters": {
    "dateFormat": "ddmmyyyy"
  },
  "preprocessingParameters": {
    "templateType": "idFront",
    "detectionMethod": "FengThreshold",
    "expandSpecsBy": 1,
    "fengAlpha": 0.11,
    "fengK1": 0.04,
    "fengK2": 0.03,
    "fengSize1": 11,
    "fengSize2": 40,
    "homomorphicFiltering": 1,
    "homomorphicFilteringAlpha": 2,
    "homomorphicFilteringBeta": 0.5,
    "homomorphicFilteringSigma": 30,
    "maxCharHeight": 80,
    "maxCharHeightHyph": 7,
    "maxCharRatio": 5.72,
    "maxCharRatioHyph": 4.5,
    "maxCharWidth": 80,
    "maxCharWidthHyph": 15,
    "medianWordDist": 15.5,
    "minCharHeight": 20,
    "minCharHeightHyph": 3,
    "minCharRatio": 0.12,
    "minCharRatioHyph": 1.2,
    "minCharWidth": 3,
    "minCharWidthHyph": 7,
    "minIntersectionRatio": 0.15,
    "minIntersectionRatioLine": 0.01,
    "wordMaxXDistance": 2.5,
    "classificationModel": "tfAUT"
  }
}