{
  "dataFields": [
    {
      "label": "surnameAndGivenNames",
      "positionIndex": 0,
      "lineIndex": 0,
      "shapeAttributes": {
        "type": "bboxUR",
        "x": 611,
        "y": 270,
        "width": 843,
        "height": 54
      },
      "type": "generic",
      "postprocessingParameterDict": {
        "validationRegex": "[A-ZÄÖÜa-zäöüß\\.\\/\\-\\(\\)\\,\\' ]{1,}",
        "cleanRegex": "[^A-ZÄÖÜa-zäöüß\\.\\/\\-\\(\\)\\,\\' ]",
        "whitelistPattern": "1,|[A-ZÄÖÜa-zäöüß\\.\\/\\-\\(\\)\\,\\' ]"
      },
      "preprocessingParameterDict": {
        "splitRatio": 1.28
      }
    },
    {
      "label": "sex",
      "positionIndex": 0,
      "lineIndex": 0,
      "shapeAttributes": {
        "type": "bboxUR",
        "x": 739,
        "y": 424,
        "width": 237,
        "height": 56
      },
      "type": "generic",
      "postprocessingParameterDict": {
        "validationRegex": "[A-ZÄÖÜa-zäöüß0-9\\.\\/\\-\\(\\)\\,\\' ]{1,}",
        "cleanRegex": "[^A-ZÄÖÜa-zäöüß0-9\\.\\/\\-\\(\\)\\,\\' ]",
        "whitelistPattern": "1,|[A-ZÄÖÜa-zäöüß0-9\\.\\/\\-\\(\\)\\,\\' ]"
      },
      "preprocessingParameterDict": {
        "splitRatio": 1.28
      }
    },
    {
      "label": "nationality",
      "positionIndex": 0,
      "lineIndex": 0,
      "shapeAttributes": {
        "type": "bboxUR",
        "x": 1349,
        "y": 427,
        "width": 108,
        "height": 47
      },
      "type": "generic",
      "postprocessingParameterDict": {
        "validationRegex": "[A-ZÄÖÜa-zäöüß0-9\\.\\/\\-\\(\\)\\,\\' ]{1,}",
        "cleanRegex": "[^A-ZÄÖÜa-zäöüß0-9\\.\\/\\-\\(\\)\\,\\' ]",
        "whitelistPattern": "1,|[A-ZÄÖÜa-zäöüß0-9\\.\\/\\-\\(\\)\\,\\' ]"
      },
      "preprocessingParameterDict": {
        "splitRatio": 1.28
      }
    },
    {
      "label": "dateOfBirth",
      "positionIndex": 0,
      "lineIndex": 0,
      "shapeAttributes": {
        "type": "bboxUR",
        "x": 1128,
        "y": 474,
        "width": 332,
        "height": 48
      },
      "type": "date",
      "postprocessingParameterDict": {
        "cleanRegex": "[^\\d]",
        "whitelistPattern": "1,|[\\d\\-\\/\\. ]",
        "validationRegex": "(19|20){1}[0-9]{2}(0[1-9]|1[0-2]){1}(0[1-9]|[12][0-9]|3[01]){1}"
      },
      "preprocessingParameterDict": {
        "splitRatio": 1.1
      }
    },
    {
      "label": "dateOfExpiry",
      "positionIndex": 0,
      "lineIndex": 0,
      "shapeAttributes": {
        "type": "bboxUR",
        "x": 1126,
        "y": 523,
        "width": 335,
        "height": 51
      },
      "type": "date",
      "postprocessingParameterDict": {
        "cleanRegex": "[^\\d]",
        "whitelistPattern": "1,|[\\d\\-\\/\\. ]",
        "validationRegex": "(19|20){1}[0-9]{2}(0[1-9]|1[0-2]){1}(0[1-9]|[12][0-9]|3[01]){1}"
      },
      "preprocessingParameterDict": {
        "splitRatio": 1.1
      }
    },
    {
      "label": "documentNumber",
      "positionIndex": 0,
      "lineIndex": 0,
      "shapeAttributes": {
        "type": "bboxUR",
        "x": 1170,
        "y": 572,
        "width": 291,
        "height": 57
      },
      "type": "documentNumber",
      "postprocessingParameterDict": {
        "validationRegex": "[0-9]{8}",
        "cleanRegex": "[^0-9]",
        "whitelistPattern": "8|[0-9]"
      },
      "preprocessingParameterDict": {
        "splitRatio": 1.28
      }
    },
    {
      "label": "cardAccessNumber",
      "positionIndex": 0,
      "lineIndex": 0,
      "shapeAttributes": {
        "type": "bboxUR",
        "x": 679,
        "y": 642,
        "width": 277,
        "height": 70
      },
      "type": "documentNumber",
      "postprocessingParameterDict": {
        "validationRegex": "[0-9]{8}",
        "cleanRegex": "[^0-9]",
        "whitelistPattern": "8|[0-9]"
      },
      "preprocessingParameterDict": {
        "splitRatio": 1.28
      }
    },
    {
      "label": "signature",
      "positionIndex": 0,
      "lineIndex": 0,
      "shapeAttributes": {
        "type": "bboxUR",
        "x": 617,
        "y": 774,
        "width": 675,
        "height": 166
      },
      "type": "image"
    },
    {
      "label": "photo",
      "positionIndex": 0,
      "lineIndex": 0,
      "shapeAttributes": {
        "type": "bboxUR",
        "x": 68,
        "y": 221,
        "width": 472,
        "height": 672
      },
      "type": "image"
    },
    {
      "label": "photo_small",
      "positionIndex": 0,
      "lineIndex": 0,
      "shapeAttributes": {
        "type": "bboxUR",
        "x": 448,
        "y": 742,
        "width": 129,
        "height": 153
      },
      "type": "image"
    },
    {
      "label": "magyarorszag_hungary",
      "positionIndex": 0,
      "lineIndex": 0,
      "shapeAttributes": {
        "type": "bboxUR",
        "x": 19,
        "y": 18,
        "width": 734,
        "height": 70
      },
      "type": "MATCHING"
    },
    {
      "label": "szemelyazonosito_igazolvany_identity_card",
      "positionIndex": 0,
      "lineIndex": 0,
      "shapeAttributes": {
        "type": "bboxUR",
        "x": 19,
        "y": 104,
        "width": 1151,
        "height": 70
      },
      "type": "MATCHING"
    },
    {
      "label": "csaladi_es_utonev",
      "positionIndex": 0,
      "lineIndex": 0,
      "shapeAttributes": {
        "type": "bboxUR",
        "x": 608,
        "y": 223,
        "width": 631,
        "height": 47
      },
      "type": "MATCHING"
    },
    {
      "label": "nem_sex",
      "positionIndex": 0,
      "lineIndex": 0,
      "shapeAttributes": {
        "type": "bboxUR",
        "x": 608,
        "y": 428,
        "width": 128,
        "height": 45
      },
      "type": "MATCHING"
    },
    {
      "label": "szuletesi_ido",
      "positionIndex": 0,
      "lineIndex": 0,
      "shapeAttributes": {
        "type": "bboxUR",
        "x": 608,
        "y": 473,
        "width": 346,
        "height": 50
      },
      "type": "MATCHING"
    },
    {
      "label": "ervenyessegi_ido",
      "positionIndex": 0,
      "lineIndex": 0,
      "shapeAttributes": {
        "type": "bboxUR",
        "x": 606,
        "y": 523,
        "width": 419,
        "height": 51
      },
      "type": "MATCHING"
    },
    {
      "label": "okmanyazonosito",
      "positionIndex": 0,
      "lineIndex": 0,
      "shapeAttributes": {
        "type": "bboxUR",
        "x": 606,
        "y": 575,
        "width": 353,
        "height": 42
      },
      "type": "MATCHING"
    },
    {
      "label": "allampolgarsag",
      "positionIndex": 0,
      "lineIndex": 0,
      "shapeAttributes": {
        "type": "bboxUR",
        "x": 995,
        "y": 430,
        "width": 353,
        "height": 47
      },
      "type": "MATCHING"
    },
    {
      "label": "can",
      "positionIndex": 0,
      "lineIndex": 0,
      "shapeAttributes": {
        "type": "bboxUR",
        "x": 602,
        "y": 648,
        "width": 77,
        "height": 53
      },
      "type": "MATCHING"
    },
    {
      "label": "alairas",
      "positionIndex": 0,
      "lineIndex": 0,
      "shapeAttributes": {
        "type": "bboxUR",
        "x": 611,
        "y": 729,
        "width": 231,
        "height": 45
      },
      "type": "MATCHING"
    }
  ],
  "height": 950,
  "width": 1500,
  "postprocessingParameters": {
    "dateFormat": "yyyymmdd"
  },
  "preprocessingParameters": {
    "templateType": "idFront",
    "detectionMethod": "FengThreshold",
    "expandSpecsBy": 1,
    "fengAlpha": 0.11,
    "fengK1": 0.04,
    "fengK2": 0.03,
    "fengSize1": 11,
    "fengSize2": 40,
    "homomorphicFiltering": 1,
    "homomorphicFilteringAlpha": 2,
    "homomorphicFilteringBeta": 0.5,
    "homomorphicFilteringSigma": 30,
    "maxCharHeight": 80,
    "maxCharHeightHyph": 7,
    "maxCharRatio": 5.72,
    "maxCharRatioHyph": 4.5,
    "maxCharWidth": 80,
    "maxCharWidthHyph": 15,
    "medianWordDist": 15.5,
    "minCharHeight": 20,
    "minCharHeightHyph": 3,
    "minCharRatio": 0.12,
    "minCharRatioHyph": 1.2,
    "minCharWidth": 3,
    "minCharWidthHyph": 7,
    "minIntersectionRatio": 0.15,
    "minIntersectionRatioLine": 0.01,
    "wordMaxXDistance": 2.5,
    "classificationModel": "tfAUT"
  }
}